setup.py
SvgTestApp.egg-info/PKG-INFO
SvgTestApp.egg-info/SOURCES.txt
SvgTestApp.egg-info/dependency_links.txt
SvgTestApp.egg-info/requires.txt
SvgTestApp.egg-info/top_level.txt
script/script.py