Metadata-Version: 1.2
Name: SvgTestApp
Version: 0.0.0.1
Summary: This is just a test
Home-page: UNKNOWN
License: UNKNOWN
Platform: UNKNOWN
Requires-Python: >=3
